README.rst
setup.py
pymetabiosis/__init__.py
pymetabiosis/bindings.py
pymetabiosis/module.py
pymetabiosis/numpy_convert.py
pymetabiosis/utils.py
pymetabiosis/wrapper.py
pymetabiosis.egg-info/PKG-INFO
pymetabiosis.egg-info/SOURCES.txt
pymetabiosis.egg-info/dependency_links.txt
pymetabiosis.egg-info/not-zip-safe
pymetabiosis.egg-info/requires.txt
pymetabiosis.egg-info/top_level.txt
pymetabiosis/__pycache__/_cffi__g83c5cf5bx6108fab5.c
pymetabiosis/__pycache__/_cffi__ge206c0b3xa70c0258.c
pymetabiosis/test/__init__.py
pymetabiosis/test/test_module.py
pymetabiosis/test/test_numpy_convert.py
pymetabiosis/test/test_wrapper.py