Metadata-Version: 1.0
Name: pymetabiosis
Version: 0.0.1
Summary: A way of using CPython 2's C extension modules on other cffi compatible Python implementations
Home-page: UNKNOWN
Author: Romain Guillebert
Author-email: romain.py@gmail.com
License: MIT
Platform: UNKNOWN
